pyarmor_runtime_000000/__init__.py
jupyter_pytest_fi_console-8.7.5.dist-info/METADATA
jupyter_pytest_fi_console-8.7.5.dist-info/WHEEL
jupyter_pytest_fi_console-8.7.5.dist-info/top_level.txt
jupyter_pytest_fi_console-8.7.5.dist-info/RECORD
