Metadata-Version: 2.1
Name: jupyter-pytest-fi-console
Version: 8.7.5
Summary: Jupyter terminal console with integreted simple pytest platform
Author: liamobrien
Author-email: liamobrien@fractureinteractive.com
Classifier: Programming Language :: Python :: 3
Classifier: License :: OSI Approved :: MIT License
Classifier: Operating System :: Microsoft :: Windows 
Requires-Python: >=3.6
Requires-Dist: psutil ==5.9.2
